bitquery_corecast_proto/__init__.py
bitquery_corecast_proto/corecast_pb2.py
bitquery_corecast_proto/corecast_pb2_grpc.py
bitquery_corecast_proto/request_pb2.py
bitquery_corecast_proto/stream_message_pb2.py
bitquery_corecast_proto-1.0.3.dist-info/licenses/LICENSE
bitquery_corecast_proto-1.0.3.dist-info/METADATA
bitquery_corecast_proto-1.0.3.dist-info/WHEEL
bitquery_corecast_proto-1.0.3.dist-info/top_level.txt
bitquery_corecast_proto-1.0.3.dist-info/RECORD
