Metadata-Version: 2.4
Name: bitquery-corecast-proto
Version: 1.0.3
Summary: gRPC protobuf definitions and generated Python code for Bitquery CoreCast Solana gRPC
Home-page: https://docs.bitquery.io/docs/category/grpc-streams/
Author: Divyasshree
Author-email: Divyasshree <divyasshree@bitquery.io>
License: MIT
Project-URL: Homepage, https://docs.bitquery.io/docs/category/grpc-streams/
Project-URL: Repository, https://github.com/bitquery/grpc-code-samples/tree/main
Project-URL: Issues, https://github.com/bitquery/grpc-code-samples/issues
Classifier: Development Status :: 4 - Beta
Classifier: Intended Audience :: Developers
Classifier: License :: OSI Approved :: MIT License
Classifier: Operating System :: OS Independent
Classifier: Programming Language :: Python :: 3
Classifier: Programming Language :: Python :: 3.8
Classifier: Programming Language :: Python :: 3.9
Classifier: Programming Language :: Python :: 3.10
Classifier: Programming Language :: Python :: 3.11
Classifier: Programming Language :: Python :: 3.12
Classifier: Topic :: Software Development :: Libraries :: Python Modules
Classifier: Topic :: System :: Networking
Requires-Python: >=3.8
License-File: LICENSE
Requires-Dist: grpcio>=1.60.0
Requires-Dist: grpcio-tools>=1.60.0
Requires-Dist: protobuf<7.0.0,>=6.30.0
Requires-Dist: bitquery-pb2-kafka-package
Dynamic: author
Dynamic: home-page
Dynamic: license-file
Dynamic: requires-python
